banner_hamsunwoo/__init__.py
banner_hamsunwoo/banner.py
banner_hamsunwoo-0.3.1.dist-info/METADATA
banner_hamsunwoo-0.3.1.dist-info/WHEEL
banner_hamsunwoo-0.3.1.dist-info/entry_points.txt
banner_hamsunwoo-0.3.1.dist-info/top_level.txt
banner_hamsunwoo-0.3.1.dist-info/RECORD
