Metadata-Version: 2.1
Name: banner_hamsunwoo
Version: 0.3.1
Summary: Banner Output Program
Author-email: sunwoo <summerham22@gmail.com>
License: MIT
Project-URL: Repository, https://github.com/hamsunwoo/banner_hamsunwoo
Project-URL: Issues, https://github.com/hamsunwoo/banner_hamsunwoo/issues
Requires-Python: >=3.8
Requires-Dist: pyfiglet >=1.0.2
